{
  "generated_at": "2026-04-06T18:26:05.170496",
  "predictions": [
    {
      "timestamp": "2026-04-06T18:00:00",
      "predicted_mw": 8799,
      "lower_bound": 8273,
      "upper_bound": 9362,
      "capacity_pct": 67.7,
      "risk_level": "safe",
      "temperature_c": 2.7
    },
    {
      "timestamp": "2026-04-06T19:00:00",
      "predicted_mw": 8743,
      "lower_bound": 8171,
      "upper_bound": 9273,
      "capacity_pct": 67.3,
      "risk_level": "safe",
      "temperature_c": 2.9
    },
    {
      "timestamp": "2026-04-06T20:00:00",
      "predicted_mw": 8651,
      "lower_bound": 8130,
      "upper_bound": 9183,
      "capacity_pct": 66.5,
      "risk_level": "safe",
      "temperature_c": 2.8
    },
    {
      "timestamp": "2026-04-06T21:00:00",
      "predicted_mw": 8523,
      "lower_bound": 8010,
      "upper_bound": 9046,
      "capacity_pct": 65.6,
      "risk_level": "safe",
      "temperature_c": 2.5
    },
    {
      "timestamp": "2026-04-06T22:00:00",
      "predicted_mw": 8366,
      "lower_bound": 7870,
      "upper_bound": 8905,
      "capacity_pct": 64.4,
      "risk_level": "safe",
      "temperature_c": 2.2
    },
    {
      "timestamp": "2026-04-06T23:00:00",
      "predicted_mw": 8204,
      "lower_bound": 7679,
      "upper_bound": 8721,
      "capacity_pct": 63.1,
      "risk_level": "safe",
      "temperature_c": 1.6
    },
    {
      "timestamp": "2026-04-07T00:00:00",
      "predicted_mw": 8055,
      "lower_bound": 7551,
      "upper_bound": 8572,
      "capacity_pct": 62.0,
      "risk_level": "safe",
      "temperature_c": 1.1
    },
    {
      "timestamp": "2026-04-07T01:00:00",
      "predicted_mw": 7937,
      "lower_bound": 7419,
      "upper_bound": 8464,
      "capacity_pct": 61.1,
      "risk_level": "safe",
      "temperature_c": 0.8
    },
    {
      "timestamp": "2026-04-07T02:00:00",
      "predicted_mw": 7859,
      "lower_bound": 7324,
      "upper_bound": 8425,
      "capacity_pct": 60.5,
      "risk_level": "safe",
      "temperature_c": 0.5
    },
    {
      "timestamp": "2026-04-07T03:00:00",
      "predicted_mw": 7829,
      "lower_bound": 7341,
      "upper_bound": 8357,
      "capacity_pct": 60.2,
      "risk_level": "safe",
      "temperature_c": 0.3
    },
    {
      "timestamp": "2026-04-07T04:00:00",
      "predicted_mw": 7858,
      "lower_bound": 7326,
      "upper_bound": 8389,
      "capacity_pct": 60.4,
      "risk_level": "safe",
      "temperature_c": -0.1
    },
    {
      "timestamp": "2026-04-07T05:00:00",
      "predicted_mw": 7948,
      "lower_bound": 7431,
      "upper_bound": 8450,
      "capacity_pct": 61.1,
      "risk_level": "safe",
      "temperature_c": -0.3
    },
    {
      "timestamp": "2026-04-07T06:00:00",
      "predicted_mw": 8092,
      "lower_bound": 7580,
      "upper_bound": 8666,
      "capacity_pct": 62.2,
      "risk_level": "safe",
      "temperature_c": -0.4
    },
    {
      "timestamp": "2026-04-07T07:00:00",
      "predicted_mw": 8263,
      "lower_bound": 7702,
      "upper_bound": 8738,
      "capacity_pct": 63.6,
      "risk_level": "safe",
      "temperature_c": -0.4
    },
    {
      "timestamp": "2026-04-07T08:00:00",
      "predicted_mw": 8422,
      "lower_bound": 7901,
      "upper_bound": 8933,
      "capacity_pct": 64.8,
      "risk_level": "safe",
      "temperature_c": -0.2
    },
    {
      "timestamp": "2026-04-07T09:00:00",
      "predicted_mw": 8537,
      "lower_bound": 7970,
      "upper_bound": 9060,
      "capacity_pct": 65.7,
      "risk_level": "safe",
      "temperature_c": 0.2
    },
    {
      "timestamp": "2026-04-07T10:00:00",
      "predicted_mw": 8597,
      "lower_bound": 8095,
      "upper_bound": 9147,
      "capacity_pct": 66.1,
      "risk_level": "safe",
      "temperature_c": 1.0
    },
    {
      "timestamp": "2026-04-07T11:00:00",
      "predicted_mw": 8620,
      "lower_bound": 8131,
      "upper_bound": 9155,
      "capacity_pct": 66.3,
      "risk_level": "safe",
      "temperature_c": 1.7
    },
    {
      "timestamp": "2026-04-07T12:00:00",
      "predicted_mw": 8633,
      "lower_bound": 8081,
      "upper_bound": 9171,
      "capacity_pct": 66.4,
      "risk_level": "safe",
      "temperature_c": 2.3
    },
    {
      "timestamp": "2026-04-07T13:00:00",
      "predicted_mw": 8653,
      "lower_bound": 8145,
      "upper_bound": 9192,
      "capacity_pct": 66.6,
      "risk_level": "safe",
      "temperature_c": 3.0
    },
    {
      "timestamp": "2026-04-07T14:00:00",
      "predicted_mw": 8683,
      "lower_bound": 8159,
      "upper_bound": 9184,
      "capacity_pct": 66.8,
      "risk_level": "safe",
      "temperature_c": 3.6
    },
    {
      "timestamp": "2026-04-07T15:00:00",
      "predicted_mw": 8720,
      "lower_bound": 8222,
      "upper_bound": 9199,
      "capacity_pct": 67.1,
      "risk_level": "safe",
      "temperature_c": 3.4
    },
    {
      "timestamp": "2026-04-07T16:00:00",
      "predicted_mw": 8745,
      "lower_bound": 8269,
      "upper_bound": 9234,
      "capacity_pct": 67.3,
      "risk_level": "safe",
      "temperature_c": 3.1
    },
    {
      "timestamp": "2026-04-07T17:00:00",
      "predicted_mw": 8746,
      "lower_bound": 8241,
      "upper_bound": 9250,
      "capacity_pct": 67.3,
      "risk_level": "safe",
      "temperature_c": 3.3
    },
    {
      "timestamp": "2026-04-07T18:00:00",
      "predicted_mw": 8731,
      "lower_bound": 8218,
      "upper_bound": 9252,
      "capacity_pct": 67.2,
      "risk_level": "safe",
      "temperature_c": 2.1
    },
    {
      "timestamp": "2026-04-07T19:00:00",
      "predicted_mw": 8689,
      "lower_bound": 8152,
      "upper_bound": 9234,
      "capacity_pct": 66.8,
      "risk_level": "safe",
      "temperature_c": 0.4
    },
    {
      "timestamp": "2026-04-07T20:00:00",
      "predicted_mw": 8606,
      "lower_bound": 8121,
      "upper_bound": 9110,
      "capacity_pct": 66.2,
      "risk_level": "safe",
      "temperature_c": -0.8
    },
    {
      "timestamp": "2026-04-07T21:00:00",
      "predicted_mw": 8477,
      "lower_bound": 7993,
      "upper_bound": 9026,
      "capacity_pct": 65.2,
      "risk_level": "safe",
      "temperature_c": -1.1
    },
    {
      "timestamp": "2026-04-07T22:00:00",
      "predicted_mw": 8325,
      "lower_bound": 7811,
      "upper_bound": 8877,
      "capacity_pct": 64.0,
      "risk_level": "safe",
      "temperature_c": -2.0
    },
    {
      "timestamp": "2026-04-07T23:00:00",
      "predicted_mw": 8159,
      "lower_bound": 7623,
      "upper_bound": 8701,
      "capacity_pct": 62.8,
      "risk_level": "safe",
      "temperature_c": -2.0
    },
    {
      "timestamp": "2026-04-08T00:00:00",
      "predicted_mw": 8009,
      "lower_bound": 7474,
      "upper_bound": 8496,
      "capacity_pct": 61.6,
      "risk_level": "safe",
      "temperature_c": -2.2
    },
    {
      "timestamp": "2026-04-08T01:00:00",
      "predicted_mw": 7891,
      "lower_bound": 7381,
      "upper_bound": 8446,
      "capacity_pct": 60.7,
      "risk_level": "safe",
      "temperature_c": -2.4
    },
    {
      "timestamp": "2026-04-08T02:00:00",
      "predicted_mw": 7811,
      "lower_bound": 7290,
      "upper_bound": 8318,
      "capacity_pct": 60.1,
      "risk_level": "safe",
      "temperature_c": -2.4
    },
    {
      "timestamp": "2026-04-08T03:00:00",
      "predicted_mw": 7782,
      "lower_bound": 7246,
      "upper_bound": 8292,
      "capacity_pct": 59.9,
      "risk_level": "safe",
      "temperature_c": -2.6
    },
    {
      "timestamp": "2026-04-08T04:00:00",
      "predicted_mw": 7809,
      "lower_bound": 7298,
      "upper_bound": 8327,
      "capacity_pct": 60.1,
      "risk_level": "safe",
      "temperature_c": -2.7
    },
    {
      "timestamp": "2026-04-08T05:00:00",
      "predicted_mw": 7900,
      "lower_bound": 7389,
      "upper_bound": 8428,
      "capacity_pct": 60.8,
      "risk_level": "safe",
      "temperature_c": -2.9
    },
    {
      "timestamp": "2026-04-08T06:00:00",
      "predicted_mw": 8045,
      "lower_bound": 7537,
      "upper_bound": 8562,
      "capacity_pct": 61.9,
      "risk_level": "safe",
      "temperature_c": -3.1
    },
    {
      "timestamp": "2026-04-08T07:00:00",
      "predicted_mw": 8218,
      "lower_bound": 7719,
      "upper_bound": 8763,
      "capacity_pct": 63.2,
      "risk_level": "safe",
      "temperature_c": -3.3
    },
    {
      "timestamp": "2026-04-08T08:00:00",
      "predicted_mw": 8380,
      "lower_bound": 7881,
      "upper_bound": 8940,
      "capacity_pct": 64.5,
      "risk_level": "safe",
      "temperature_c": -3.5
    },
    {
      "timestamp": "2026-04-08T09:00:00",
      "predicted_mw": 8495,
      "lower_bound": 7978,
      "upper_bound": 9046,
      "capacity_pct": 65.3,
      "risk_level": "safe",
      "temperature_c": -3.0
    },
    {
      "timestamp": "2026-04-08T10:00:00",
      "predicted_mw": 8556,
      "lower_bound": 8023,
      "upper_bound": 9082,
      "capacity_pct": 65.8,
      "risk_level": "safe",
      "temperature_c": -2.3
    },
    {
      "timestamp": "2026-04-08T11:00:00",
      "predicted_mw": 8580,
      "lower_bound": 8059,
      "upper_bound": 9133,
      "capacity_pct": 66.0,
      "risk_level": "safe",
      "temperature_c": -1.7
    },
    {
      "timestamp": "2026-04-08T12:00:00",
      "predicted_mw": 8594,
      "lower_bound": 8033,
      "upper_bound": 9134,
      "capacity_pct": 66.1,
      "risk_level": "safe",
      "temperature_c": -1.1
    },
    {
      "timestamp": "2026-04-08T13:00:00",
      "predicted_mw": 8613,
      "lower_bound": 8090,
      "upper_bound": 9178,
      "capacity_pct": 66.3,
      "risk_level": "safe",
      "temperature_c": -0.4
    },
    {
      "timestamp": "2026-04-08T14:00:00",
      "predicted_mw": 8643,
      "lower_bound": 8109,
      "upper_bound": 9184,
      "capacity_pct": 66.5,
      "risk_level": "safe",
      "temperature_c": 0.3
    },
    {
      "timestamp": "2026-04-08T15:00:00",
      "predicted_mw": 8673,
      "lower_bound": 8142,
      "upper_bound": 9202,
      "capacity_pct": 66.7,
      "risk_level": "safe",
      "temperature_c": 0.9
    },
    {
      "timestamp": "2026-04-08T16:00:00",
      "predicted_mw": 8690,
      "lower_bound": 8140,
      "upper_bound": 9200,
      "capacity_pct": 66.8,
      "risk_level": "safe",
      "temperature_c": 1.6
    },
    {
      "timestamp": "2026-04-08T17:00:00",
      "predicted_mw": 8686,
      "lower_bound": 8145,
      "upper_bound": 9187,
      "capacity_pct": 66.8,
      "risk_level": "safe",
      "temperature_c": 2.3
    }
  ]
}